README.md
setup.cfg
setup.py
fairsearchcore/__init__.py
fairsearchcore/fail_prob.py
fairsearchcore/fair.py
fairsearchcore/models.py
fairsearchcore/mtable_generator.py
fairsearchcore/re_ranker.py
fairsearchcore/simulator.py
fairsearchcore.egg-info/PKG-INFO
fairsearchcore.egg-info/SOURCES.txt
fairsearchcore.egg-info/dependency_links.txt
fairsearchcore.egg-info/requires.txt
fairsearchcore.egg-info/top_level.txt