Metadata-Version: 1.2
Name: fairsearchcore
Version: 1.0.2
Summary: A Python library with the core algorithms used to do fair search. 
Home-page: https://github.com/fair-search/fairsearchcore-python
Author: Ivan Kitanovski
Author-email: ivan.kitanovski@gmail.com
License: Apache 2.0
Keywords: search,fairness,fa*ir,ranking,reranking
Platform: UNKNOWN
Classifier: Development Status :: 5 - Production/Stable
Classifier: Intended Audience :: Developers
Classifier: Natural Language :: English
Classifier: License :: OSI Approved :: Apache Software License
Classifier: Programming Language :: Python
Classifier: Programming Language :: Python :: 3
Classifier: Programming Language :: Python :: 3.4
Classifier: Programming Language :: Python :: 3.5
Classifier: Programming Language :: Python :: 3.6
Classifier: Programming Language :: Python :: 3.7
Classifier: Programming Language :: Python :: Implementation :: PyPy
Requires-Python: >=3.0
